balanceai/__init__.py
balanceai/cli_runner.py
balanceai/config/__init__.py
balanceai/config/configuration.py
balanceai/huggingface/Huggingface.py
balanceai/huggingface/__init__.py
balanceai/huggingface/server.py
balanceai/init/Init.py
balanceai/init/__init__.py
balanceai/validate/Validate.py
balanceai/validate/__init__.py
balanceai/wrapper/__init__.py
balanceai/wrapper/server.py
balanceai/wrapper/ai/AiHttpClient.py
balanceai/wrapper/ai/AiService.py
balanceai/wrapper/ai/__init__.py
balanceai/wrapper/chain/ChainHttpClient.py
balanceai/wrapper/chain/ChainService.py
balanceai/wrapper/chain/UsageInfoDataGenerator.py
balanceai/wrapper/chain/__init__.py
balanceai/wrapper/docker/Docker.py
balanceai/wrapper/docker/__init__.py
balanceai/wrapper/ipfs/IpfsHttpClient.py
balanceai/wrapper/ipfs/IpfsService.py
balanceai/wrapper/ipfs/TransactionDataGenerator.py
balanceai/wrapper/ipfs/__init__.py
balanceai/wrapper/signature/SignatureService.py
balanceai/wrapper/signature/__init__.py
balanceai/zkml/Zkml.py
balanceai/zkml/__init__.py
balanceai-0.0.2.dist-info/METADATA
balanceai-0.0.2.dist-info/WHEEL
balanceai-0.0.2.dist-info/entry_points.txt
balanceai-0.0.2.dist-info/licenses/LICENSE
balanceai-0.0.2.dist-info/RECORD
