Metadata-Version: 2.3
Name: Balanceai
Version: 0.0.2
Summary: BalanceAI Wrapper enables connection of AI models (API endpoints to AI models) to the BalanceAI blockchain. Wrapper is a Python utility (command-line tools and libraries) that wraps API calls from locally run model APIs, exposing them to BalanceAI users. It provides security by validating requests from authenticated users, checking authorization, and storing information about requests/responses on-chain and in the InterPlanetary File System (IPFS).
Project-URL: Homepage, https://www.balanceai.network/
Project-URL: Issues, https://github.com/balanceainetwork/balanceai-wrapper/issues
Project-URL: Repository, https://github.com/balanceainetwork/balanceai-wrapper.git
Author-email: BalanceAI <ai@balanceai.network>
License:                     GNU AFFERO GENERAL PUBLIC LICENSE
License-File: LICENSE
Keywords: BAI,BalanceAI,ai,blockchain,web3
Classifier: License :: OSI Approved :: GNU Affero General Public License v3 or later (AGPLv3+)
Classifier: Operating System :: OS Independent
Classifier: Programming Language :: Python :: 3
Requires-Python: >=3.12
Requires-Dist: argparse==1.4.0
Requires-Dist: flask==3.0.2
Requires-Dist: requests==2.31.0
